dynamics/__init__.py
dynamics/dynamics.cpython-38-x86_64-linux-gnu.so
dynamics/visualize.py
rdynamics_py-0.1.0.dist-info/METADATA
rdynamics_py-0.1.0.dist-info/WHEEL
rdynamics_py-0.1.0.dist-info/licenses/LICENSE
rdynamics_py-0.1.0.dist-info/RECORD
