Metadata-Version: 2.4
Name: rdynamics-py
Version: 0.1.0
Classifier: Programming Language :: Rust
Classifier: Programming Language :: Python :: Implementation :: CPython
Classifier: Programming Language :: Python :: Implementation :: PyPy
License-File: LICENSE
Summary: An experimental implementation of Rigid Body Dynamics algorithms.
Author-email: Antoine Groudiev <antoine.groudiev@ens.psl.eu>
Requires-Python: >=3.8
